xcorduroy/DEM.py
xcorduroy/__init__.py
xcorduroy/accessors.py
xcorduroy/types.py
xcorduroy-0.0.2.dist-info/WHEEL
xcorduroy-0.0.2.dist-info/METADATA
xcorduroy-0.0.2.dist-info/RECORD
