Metadata-Version: 2.3
Name: xcorduroy
Version: 0.0.2
Summary: Dask aware lightweight DEM utilities for Xarray
Requires-Dist: dask>=2025.12.0
Requires-Dist: numpy>=2.1.0
Requires-Dist: xarray>=2025.12.0
Requires-Dist: xproj>=0.2.1
Requires-Python: >=3.13
